simetri/.gitignore
simetri/__init__.py
simetri/.vscode/launch.json
simetri/.vscode/settings.json
simetri/canvas/canvas.py
simetri/canvas/draw.py
simetri/canvas/grids.py
simetri/canvas/style_map.py
simetri/colors/__init__.py
simetri/colors/colors.py
simetri/colors/palettes.py
simetri/colors/swatches.py
simetri/curves/bezier.ipynb
simetri/extensions/__init__.py
simetri/extensions/easing.py
simetri/extensions/l_system.py
simetri/extensions/music.py
simetri/extensions/ndfsm.py
simetri/extensions/turtle_sg.py
simetri/frieze/__init__.py
simetri/frieze/frieze.py
simetri/geometry/__init__.py
simetri/geometry/bezier.py
simetri/geometry/circle.py
simetri/geometry/ellipse.py
simetri/geometry/geometry.py
simetri/geometry/hobby.py
simetri/geometry/sine.py
simetri/graphics/__init__.py
simetri/graphics/affine.py
simetri/graphics/all_enums.py
simetri/graphics/batch.py
simetri/graphics/bbox.py
simetri/graphics/common.py
simetri/graphics/core.py
simetri/graphics/dots.py
simetri/graphics/merge.py
simetri/graphics/path.py
simetri/graphics/pattern.py
simetri/graphics/points.py
simetri/graphics/shape.py
simetri/graphics/shapes.py
simetri/graphics/sketch.py
simetri/helpers/__init__.py
simetri/helpers/constraint_solver.py
simetri/helpers/graph.py
simetri/helpers/hello.py
simetri/helpers/illustration.py
simetri/helpers/modifiers.py
simetri/helpers/utilities.py
simetri/helpers/validation.py
simetri/helpers/vector.py
simetri/lace/__init__.py
simetri/lace/lace.py
simetri/notebook/__init__.py
simetri/settings/settings.py
simetri/stars/__init__.py
simetri/stars/stars.py
simetri/tikz/__init__.py
simetri/tikz/tikz.py
simetri/wallpaper/__init__.py
simetri/wallpaper/wallpaper.py
simetri-0.0.6.dist-info/METADATA
simetri-0.0.6.dist-info/WHEEL
simetri-0.0.6.dist-info/entry_points.txt
simetri-0.0.6.dist-info/licenses/LICENSE
simetri-0.0.6.dist-info/RECORD
